CHANGELOG.md
README.md
monkeytypes/__init__.py
monkeytypes/agent_plugin_manifest.py
monkeytypes/agent_plugin_type.py
monkeytypes/b64_bytes.py
monkeytypes/base_models.py
monkeytypes/concurrency.py
monkeytypes/credentials/__init__.py
monkeytypes/credentials/credentials.py
monkeytypes/credentials/email_address.py
monkeytypes/credentials/encoding.py
monkeytypes/credentials/lm_hash.py
monkeytypes/credentials/nt_hash.py
monkeytypes/credentials/password.py
monkeytypes/credentials/ssh_keypair.py
monkeytypes/credentials/username.py
monkeytypes/credentials/validators.py
monkeytypes/file_extension.py
monkeytypes/ids.py
monkeytypes/int_range.py
monkeytypes/network_range.py
monkeytypes/networking.py
monkeytypes/operating_system.py
monkeytypes/percent.py
monkeytypes/py.typed
monkeytypes/secrets.py
monkeytypes/serialization.py
monkey_types-1.1.0.dist-info/LICENSE
monkey_types-1.1.0.dist-info/METADATA
monkey_types-1.1.0.dist-info/WHEEL
monkey_types-1.1.0.dist-info/RECORD
